[
  {"titulo":"Dato Curioso #1","categoria":"Ciencia","descripcion":"La miel nunca se echa a perder y se han encontrado tarros comestibles de más de 3000 años en tumbas egipcias."},
  {"titulo":"Dato Curioso #2","categoria":"Animales","descripcion":"El corazón de un camarón está en su cabeza."},
  {"titulo":"Dato Curioso #3","categoria":"Ciencia","descripcion":"Los pulpos tienen tres corazones y sangre azul."},
  {"titulo":"Dato Curioso #4","categoria":"Historia","descripcion":"Cleopatra vivió más cerca del lanzamiento del iPhone que de la construcción de las pirámides."},
  {"titulo":"Dato Curioso #5","categoria":"Animales","descripcion":"Los gatos no pueden saborear lo dulce."},
  {"titulo":"Dato Curioso #6","categoria":"Ciencia","descripcion":"El ADN humano y el plátano comparten aproximadamente un 60% de similitud genética."},
  {"titulo":"Dato Curioso #7","categoria":"Historia","descripcion":"Napoleón era casi imposible de medir con exactitud porque sus coronas variaban según la fuente."},
  {"titulo":"Dato Curioso #8","categoria":"Animales","descripcion":"Las jirafas tienen la misma cantidad de vértebras en el cuello que los humanos: siete."},
  {"titulo":"Dato Curioso #9","categoria":"Ciencia","descripcion":"Existen más átomos en un vaso de agua que vasos de agua en todos los océanos de la Tierra."},
  {"titulo":"Dato Curioso #10","categoria":"Animales","descripcion":"Los tiburones existían antes que los árboles, hace más de 400 millones de años."},
  {"titulo":"Dato Curioso #11","categoria":"Historia","descripcion":"El primer código de barras se escaneó en 1974 y era un paquete de chicles."},
  {"titulo":"Dato Curioso #12","categoria":"Ciencia","descripcion":"El corazón humano genera suficiente presión al latir que podría lanzar sangre hasta 9 metros de distancia."},
  {"titulo":"Dato Curioso #13","categoria":"Animales","descripcion":"Los caballitos de mar macho son los que se embarazan y dan a luz."},
  {"titulo":"Dato Curioso #14","categoria":"Historia","descripcion":"El papel moneda se inventó en China alrededor del año 700 d.C."},
  {"titulo":"Dato Curioso #15","categoria":"Ciencia","descripcion":"El sol libera más energía en un segundo que toda la energía consumida por la humanidad en un año."},
  {"titulo":"Dato Curioso #16","categoria":"Animales","descripcion":"Los pulpos pueden cambiar de color y textura para camuflarse con su entorno."},
  {"titulo":"Dato Curioso #17","categoria":"Historia","descripcion":"La Gran Muralla China no es visible desde la luna con el ojo humano."},
  {"titulo":"Dato Curioso #18","categoria":"Ciencia","descripcion":"El agua puede hervir y congelarse al mismo tiempo en un fenómeno llamado 'punto triple'."},
  {"titulo":"Dato Curioso #19","categoria":"Animales","descripcion":"Las hormigas pueden levantar objetos 50 veces su peso."},
  {"titulo":"Dato Curioso #20","categoria":"Historia","descripcion":"En la antigua Roma, existían orinas usadas como detergente para lavar ropa."},
  {"titulo":"Dato Curioso #21","categoria":"Ciencia","descripcion":"El cerebro humano consume más energía que cualquier otro órgano, incluso en reposo."},
  {"titulo":"Dato Curioso #22","categoria":"Animales","descripcion":"Los koalas duermen hasta 22 horas al día."},
  {"titulo":"Dato Curioso #23","categoria":"Historia","descripcion":"El reloj mecánico más antiguo que se conoce data del siglo XIV."},
  {"titulo":"Dato Curioso #24","categoria":"Ciencia","descripcion":"El sonido viaja más rápido en el agua que en el aire."},
  {"titulo":"Dato Curioso #25","categoria":"Animales","descripcion":"Los delfines tienen nombres propios y se llaman entre sí usando silbidos únicos."},
  {"titulo":"Dato Curioso #26","categoria":"Historia","descripcion":"El faraón Ramsés II vivió más de 90 años, un récord para la época."},
  {"titulo":"Dato Curioso #27","categoria":"Ciencia","descripcion":"Un rayo puede calentar el aire a más de 30,000 grados Celsius, cinco veces la temperatura del sol."},
  {"titulo":"Dato Curioso #28","categoria":"Animales","descripcion":"Las arañas no pueden volar, pero algunas especies usan hilos de seda para desplazarse con el viento."},
  {"titulo":"Dato Curioso #29","categoria":"Historia","descripcion":"El calendario gregoriano fue introducido en 1582 por el Papa Gregorio XIII."},
  {"titulo":"Dato Curioso #30","categoria":"Ciencia","descripcion":"Los agujeros negros no 'succionan' todo, solo afectan a objetos que se acercan demasiado."},
  {"titulo":"Dato Curioso #31","categoria":"Animales","descripcion":"El corazón de una ballena azul es tan grande que un humano podría nadar por sus arterias."},
  {"titulo":"Dato Curioso #32","categoria":"Historia","descripcion":"El primer submarino funcional fue construido en 1620."},
  {"titulo":"Dato Curioso #33","categoria":"Ciencia","descripcion":"La luz tarda 8 minutos y 20 segundos en viajar del sol a la Tierra."},
  {"titulo":"Dato Curioso #34","categoria":"Animales","descripcion":"Los elefantes pueden comunicarse usando sonidos que los humanos no pueden escuchar."},
  {"titulo":"Dato Curioso #35","categoria":"Historia","descripcion":"La bandera más antigua aún en uso tiene más de 700 años."},
  {"titulo":"Dato Curioso #36","categoria":"Ciencia","descripcion":"Un solo rayo contiene suficiente energía para alimentar una ciudad pequeña por un día."},
  {"titulo":"Dato Curioso #37","categoria":"Animales","descripcion":"Los camaleones no solo cambian de color, sino también su visión es independiente para cada ojo."},
  {"titulo":"Dato Curioso #38","categoria":"Historia","descripcion":"El papel higiénico se inventó en China en el siglo XIV."},
  {"titulo":"Dato Curioso #39","categoria":"Ciencia","descripcion":"El oxígeno que respiramos hoy proviene de organismos que vivieron hace millones de años."},
  {"titulo":"Dato Curioso #40","categoria":"Animales","descripcion":"Los murciélagos son los únicos mamíferos capaces de volar."},
  {"titulo":"Dato Curioso #41","categoria":"Historia","descripcion":"El primer correo electrónico fue enviado en 1971."},
  {"titulo":"Dato Curioso #42","categoria":"Ciencia","descripcion":"Los volcanes submarinos crean islas que pueden emerger y desaparecer en pocos años."},
  {"titulo":"Dato Curioso #43","categoria":"Animales","descripcion":"Las libélulas pueden volar hacia atrás."},
  {"titulo":"Dato Curioso #44","categoria":"Historia","descripcion":"El primer automóvil de gasolina fue construido en 1885 por Karl Benz."},
  {"titulo":"Dato Curioso #45","categoria":"Ciencia","descripcion":"El chocolate puede ser mortal para los perros, incluso en pequeñas cantidades."},
  {"titulo":"Dato Curioso #46","categoria":"Animales","descripcion":"Las tortugas pueden respirar a través de su trasero."},
  {"titulo":"Dato Curioso #47","categoria":"Historia","descripcion":"La torre Eiffel iba a ser demolida después de 20 años de su construcción."},
  {"titulo":"Dato Curioso #48","categoria":"Ciencia","descripcion":"El hielo seco no se derrite, se sublima directamente de sólido a gas."},
  {"titulo":"Dato Curioso #49","categoria":"Animales","descripcion":"Los cuervos pueden reconocer rostros humanos y recordarlos por años."},
  {"titulo":"Dato Curioso #50","categoria":"Historia","descripcion":"El primer supermercado abrió en 1916 en Memphis, Tennessee."},
  {"titulo":"Dato Curioso #51","categoria":"Ciencia","descripcion":"El ADN puede enrollarse y medir hasta dos metros dentro de cada célula humana."},
  {"titulo":"Dato Curioso #52","categoria":"Animales","descripcion":"Los camellos pueden beber hasta 135 litros de agua en 13 minutos."},
  {"titulo":"Dato Curioso #53","categoria":"Historia","descripcion":"El Titanic tenía botes salvavidas para solo la mitad de sus pasajeros."},
  {"titulo":"Dato Curioso #54","categoria":"Ciencia","descripcion":"El cerebro puede generar suficiente electricidad para encender una bombilla pequeña."},
  {"titulo":"Dato Curioso #55","categoria":"Animales","descripcion":"Las ranas pueden congelarse durante el invierno y descongelarse sin morir."},
  {"titulo":"Dato Curioso #56","categoria":"Historia","descripcion":"La ciudad de Venecia tiene más de 400 puentes."},
  {"titulo":"Dato Curioso #57","categoria":"Ciencia","descripcion":"Los rayos cósmicos que nos golpean provienen de fuera del sistema solar."},
  {"titulo":"Dato Curioso #58","categoria":"Animales","descripcion":"El colibrí es el único pájaro que puede volar hacia atrás."},
  {"titulo":"Dato Curioso #59","categoria":"Historia","descripcion":"El Coliseo Romano podía albergar hasta 50,000 espectadores."},
  {"titulo":"Dato Curioso #60","categoria":"Ciencia","descripcion":"El metal más liviano conocido es el aerogel, que flota en el aire."},
  {"titulo":"Dato Curioso #61","categoria":"Animales","descripcion":"Los delfines duermen con un hemisferio del cerebro activo y el otro descansando."},
  {"titulo":"Dato Curioso #62","categoria":"Historia","descripcion":"La primera máquina expendedora fue inventada en el siglo I en Egipto y dispensaba agua bendita."},
  {"titulo":"Dato Curioso #63","categoria":"Ciencia","descripcion":"El sonido no puede viajar en el vacío porque necesita un medio material."},
  {"titulo":"Dato Curioso #64","categoria":"Animales","descripcion":"Las ballenas azules pueden medir hasta 30 metros y pesar más de 150 toneladas."},
  {"titulo":"Dato Curioso #65","categoria":"Historia","descripcion":"El primer telescopio fue construido en 1608 por Hans Lippershey."},
  {"titulo":"Dato Curioso #66","categoria":"Ciencia","descripcion":"La velocidad de la luz es de aproximadamente 299,792 km/s."},
  {"titulo":"Dato Curioso #67","categoria":"Animales","descripcion":"Los pulpos pueden regenerar sus brazos si los pierden."},
  {"titulo":"Dato Curioso #68","categoria":"Historia","descripcion":"La Gran Depresión comenzó en 1929 con el colapso de la Bolsa de Nueva York."},
  {"titulo":"Dato Curioso #69","categoria":"Ciencia","descripcion":"Las medusas inmortales, como la Turritopsis dohrnii, pueden revertir su ciclo de vida."},
  {"titulo":"Dato Curioso #70","categoria":"Animales","descripcion":"Las abejas pueden reconocer rostros humanos."},
  {"titulo":"Dato Curioso #71","categoria":"Historia","descripcion":"La Torre de Pisa se inclinó durante su construcción debido al suelo blando."},
  {"titulo":"Dato Curioso #72","categoria":"Ciencia","descripcion":"El universo observable tiene un diámetro de aproximadamente 93 mil millones de años luz."},
  {"titulo":"Dato Curioso #73","categoria":"Animales","descripcion":"Los gatos domésticos pueden correr a más de 48 km/h."},
  {"titulo":"Dato Curioso #74","categoria":"Historia","descripcion":"El primer mapa impreso conocido data de 1472."},
  {"titulo":"Dato Curioso #75","categoria":"Ciencia","descripcion":"El corazón de un colibrí puede latir hasta 1200 veces por minuto."},
  {"titulo":"Dato Curioso #76","categoria":"Animales","descripcion":"Los camaleones tienen una lengua más larga que su cuerpo que usan para cazar."},
  {"titulo":"Dato Curioso #77","categoria":"Historia","descripcion":"La primera vacuna contra la viruela fue creada por Edward Jenner en 1796."},
  {"titulo":"Dato Curioso #78","categoria":"Ciencia","descripcion":"Los rayos son más calientes que la superficie del sol."},
  {"titulo":"Dato Curioso #79","categoria":"Animales","descripcion":"Los tiburones no tienen huesos, solo cartílago."},
  {"titulo":"Dato Curioso #80","categoria":"Historia","descripcion":"La biblioteca de Alejandría fue una de las más grandes de la antigüedad y fue destruida en varias ocasiones."},
  {"titulo":"Dato Curioso #81","categoria":"Ciencia","descripcion":"El titanio es resistente a la corrosión y extremadamente fuerte para su peso."},
  {"titulo":"Dato Curioso #82","categoria":"Animales","descripcion":"Los elefantes usan herramientas y tienen memoria excelente."},
  {"titulo":"Dato Curioso #83","categoria":"Historia","descripcion":"La penicilina fue descubierta accidentalmente por Alexander Fleming en 1928."},
  {"titulo":"Dato Curioso #84","categoria":"Ciencia","descripcion":"El magnetismo de la Tierra protege al planeta de la radiación cósmica."},
  {"titulo":"Dato Curioso #85","categoria":"Animales","descripcion":"Los loros grises africanos pueden imitar el habla humana con precisión."},
  {"titulo":"Dato Curioso #86","categoria":"Historia","descripcion":"El primer puente colgante de acero se construyó en 1801 en Inglaterra."},
  {"titulo":"Dato Curioso #87","categoria":"Ciencia","descripcion":"El planeta más caliente del sistema solar es Venus, no Mercurio."},
  {"titulo":"Dato Curioso #88","categoria":"Animales","descripcion":"Los cangrejos violinistas usan sus grandes pinzas para comunicarse y atraer parejas."},
  {"titulo":"Dato Curioso #89","categoria":"Historia","descripcion":"La Revolución Francesa comenzó en 1789 y marcó el fin del Antiguo Régimen."},
  {"titulo":"Dato Curioso #90","categoria":"Ciencia","descripcion":"La energía oscura representa aproximadamente el 68% del universo."},
  {"titulo":"Dato Curioso #91","categoria":"Animales","descripcion":"Los pingüinos emperador pueden sumergirse a más de 500 metros bajo el agua."},
  {"titulo":"Dato Curioso #92","categoria":"Historia","descripcion":"La escritura cuneiforme se inventó hace más de 5000 años en Mesopotamia."},
  {"titulo":"Dato Curioso #93","categoria":"Ciencia","descripcion":"El genoma humano contiene aproximadamente 3 mil millones de pares de bases."},
  {"titulo":"Dato Curioso #94","categoria":"Animales","descripcion":"Las estrellas de mar pueden regenerar brazos perdidos y, en algunos casos, un cuerpo entero."},
  {"titulo":"Dato Curioso #95","categoria":"Historia","descripcion":"El primer ferrocarril público se inauguró en 1825 en Inglaterra."},
  {"titulo":"Dato Curioso #96","categoria":"Ciencia","descripcion":"Los huracanes pueden liberar energía equivalente a varias bombas atómicas por segundo."},
  {"titulo":"Dato Curioso #97","categoria":"Animales","descripcion":"Los caballos pueden dormir de pie gracias a un sistema de ligamentos que bloquea sus patas."},
  {"titulo":"Dato Curioso #98","categoria":"Historia","descripcion":"El primer teléfono fue inventado por Alexander Graham Bell en 1876."},
  {"titulo":"Dato Curioso #99","categoria":"Ciencia","descripcion":"La luna se aleja de la Tierra aproximadamente 3.8 cm por año."},
  {"titulo":"Dato Curioso #100","categoria":"Animales","descripcion":"El pulpo Dumbo usa sus aletas como orejas para nadar elegantemente."}
]
